{
	"credit": "Made with Blockbench",
	"textures": {
		"0": "wilderworld:block/shelfshroom",
		"particle": "wilderworld:block/shelfshroom"
	},
	"elements": [
		{
			"from": [11, 19, -2],
			"to": [15, 19, 14],
			"rotation": {"angle": -22.5, "axis": "z", "origin": [-10, 11, 1]},
			"faces": {
				"north": {"uv": [0, 0, 16, 0], "texture": "#0"},
				"east": {"uv": [0, 0, 16, 0], "texture": "#0"},
				"south": {"uv": [0, 0, 16, 0], "texture": "#0"},
				"west": {"uv": [0, 0, 16, 0], "texture": "#0"},
				"up": {"uv": [0, 3, 16, 7], "rotation": 90, "texture": "#0"},
				"down": {"uv": [0, 3, 16, 7], "rotation": 270, "texture": "#0"}
			}
		},
		{
			"from": [11, 16, 1],
			"to": [15, 16, 17],
			"rotation": {"angle": -22.5, "axis": "z", "origin": [-10, 7, 1]},
			"faces": {
				"north": {"uv": [0, 0, 16, 0], "texture": "#0"},
				"east": {"uv": [0, 0, 16, 0], "texture": "#0"},
				"south": {"uv": [0, 0, 16, 0], "texture": "#0"},
				"west": {"uv": [0, 0, 16, 0], "texture": "#0"},
				"up": {"uv": [0, 7, 16, 11], "rotation": 90, "texture": "#0"},
				"down": {"uv": [0, 7, 16, 11], "rotation": 270, "texture": "#0"}
			}
		},
		{
			"from": [11, 13, 2],
			"to": [15, 13, 18],
			"rotation": {"angle": -22.5, "axis": "z", "origin": [-10, 4, 1]},
			"faces": {
				"north": {"uv": [0, 0, 16, 0], "texture": "#0"},
				"east": {"uv": [0, 0, 16, 0], "texture": "#0"},
				"south": {"uv": [0, 0, 16, 0], "texture": "#0"},
				"west": {"uv": [0, 0, 16, 0], "texture": "#0"},
				"up": {"uv": [0, 3, 16, 7], "rotation": 90, "texture": "#0"},
				"down": {"uv": [0, 3, 16, 7], "rotation": 270, "texture": "#0"}
			}
		},
		{
			"from": [11, 22, 1],
			"to": [15, 22, 17],
			"rotation": {"angle": -22.5, "axis": "z", "origin": [-10, 14, 1]},
			"faces": {
				"north": {"uv": [0, 0, 16, 0], "texture": "#0"},
				"east": {"uv": [0, 0, 16, 0], "texture": "#0"},
				"south": {"uv": [0, 0, 16, 0], "texture": "#0"},
				"west": {"uv": [0, 0, 16, 0], "texture": "#0"},
				"up": {"uv": [0, 11, 16, 15], "rotation": 90, "texture": "#0"},
				"down": {"uv": [0, 11, 16, 15], "rotation": 270, "texture": "#0"}
			}
		}
	]
}